hruid/__init__.py
hruid/__main__.py
hruid/adjectives.py
hruid/adverbs.py
hruid/cli.py
hruid/hruid.py
hruid/nouns.py
hruid/verbs.py
hruid-0.0.3.dist-info/entry_points.txt
hruid-0.0.3.dist-info/LICENSE
hruid-0.0.3.dist-info/WHEEL
hruid-0.0.3.dist-info/METADATA
hruid-0.0.3.dist-info/RECORD
