Metadata-Version: 2.1
Name: hruid
Version: 0.0.3
Summary: Human Readable Unique Identifiers for Python
Home-page: https://github.com/nebbles/hruid-python
Author: nebbles
Requires-Python: >=3.7,<4.0
Classifier: Environment :: Console
Classifier: Intended Audience :: Developers
Classifier: License :: OSI Approved :: GNU General Public License v3 (GPLv3)
Classifier: Natural Language :: English
Classifier: Operating System :: OS Independent
Classifier: Programming Language :: Python :: 3
Classifier: Programming Language :: Python :: 3.7
Classifier: Topic :: Utilities
